{
  "aor": 0.0005090812720848056,
  "aqi": 0.005955246501766784,
  "bids_meta": {
    "MultiBandFactor": 1,
    "RepetitionTime": 2.0,
    "SliceOrder": "ascending",
    "TaskName": "RLtestphase",
    "dataset": "ds002543",
    "modality": "bold",
    "run_id": 3,
    "subject_id": "009",
    "task_id": "RLtestphase"
  },
  "dummy_trs": 0,
  "dvars_nstd": 18.648979819432626,
  "dvars_std": 1.1404311530851057,
  "dvars_vstd": 0.9786823226595748,
  "efc": 0.43361023089950146,
  "fber": 2367757.25,
  "fd_mean": 0.21795673707974808,
  "fd_num": 144,
  "fd_perc": 50.88339222614841,
  "fwhm_avg": 2.026149200637722,
  "fwhm_x": 1.9764733333333335,
  "fwhm_y": 2.2918499999999997,
  "fwhm_z": 1.8101242685798338,
  "gcor": 0.0277609,
  "gsr_x": -0.010930878110229969,
  "gsr_y": 0.012007727287709713,
  "provenance": {
    "md5sum": "b8fa18c039e818af32c8646eaf76b94b",
    "settings": {
      "fd_thres": 0.2,
      "testing": false
    },
    "software": "mriqc",
    "version": "22.0.1",
    "webapi_port": null,
    "webapi_url": "https://mriqc.nimh.nih.gov/api/v1"
  },
  "size_t": 283,
  "size_x": 80,
  "size_y": 80,
  "size_z": 37,
  "snr": 5.451514104631468,
  "spacing_tr": 2.0,
  "spacing_x": 3.0,
  "spacing_y": 3.0,
  "spacing_z": 3.299999952316284,
  "summary_bg_k": 29.5193411343172,
  "summary_bg_mad": 0.9785967178072064,
  "summary_bg_mean": 30.26309585571289,
  "summary_bg_median": 0.6667748689651489,
  "summary_bg_n": 159889.0,
  "summary_bg_p05": 0.005069609731435776,
  "summary_bg_p95": 190.63154296875,
  "summary_bg_stdv": 85.23033142089844,
  "summary_fg_k": 4.1390438621954795,
  "summary_fg_mad": 151.21673916519734,
  "summary_fg_mean": 1033.9720458984375,
  "summary_fg_median": 1014.1177368164062,
  "summary_fg_n": 35378.0,
  "summary_fg_p05": 788.9871032714843,
  "summary_fg_p95": 1314.3522644042969,
  "summary_fg_stdv": 186.0223388671875,
  "tsnr": 74.82106018066406
}